[{
    "id": 1,
    "name": "ppp",
    "color": "#008080"
  },
  {
    "id": 2,
    "name": "SD",
    "color": "#2E86C1"
  },
  {
    "id": 3,
    "name": "Vardy",
    "color": "#7B241C"
  },
  {
    "id": 4,
    "name": "T",
    "color": "#CD5C5C"
  },
  {
    "id": 5,
    "name": "L1",
    "color": "#F4D03F"
  },
  {
    "id": 6,
    "name": "NE",
    "color": "#C39BD3"
  },
  {
    "id": 7,
    "name": "lek",
    "color": "#BFC9CA"
  },
  {
    "id": 8,
    "name": "Gof",
    "color": "#AED6F1"
  },
  {
    "id": 9,
    "name": "BigBee",
    "color": "D98880"
  },
  {
    "id": 10,
    "name": "cherub",
    "color": "#A9DFBF"
  },
  {
    "id": 11,
    "name": "ekkau",
    "color": "#FFA07A"
  },
  {
    "id": 12,
    "name": "Mac",
    "color": "#7D3C98"
  },
  {
    "id": 13,
    "name": "MSalah",
    "color": "#9A7D0A"
  },
  {
    "id": 14,
    "name": "ภัทร",
    "color": "#566573"
  },
  {
    "id": 15,
    "name": "BY",
    "color": "#76D7C4"
  },
  {
    "id": 16,
    "name": "kob",
    "color": "#154360"
  },
  {
    "id": 17,
    "name": "Suthep",
    "color": "#27AE60"
  },
  {
    "id": 18,
    "name": "Theerathorn",
    "color": "#CB4335"
  },
  {
    "id": 19,
    "name": "Berm",
    "color": "#F9E79F"
  },
  {
    "id": 20,
    "name": "ARM",
    "color": "#E59866"
  }
]